veritax_analytics/__init__.py
veritax_analytics/buffer.py
veritax_analytics/client.py
veritax_analytics/exceptions.py
veritax_analytics/models.py
veritax_analytics/trace.py
veritax_analytics/trace_context.py
veritax_analytics/trace_manager.py
veritax_analytics/transport.py
veritax_analytics/utils.py
veritax_analytics-1.0.0.dist-info/METADATA
veritax_analytics-1.0.0.dist-info/WHEEL
veritax_analytics-1.0.0.dist-info/RECORD
