Metadata-Version: 2.4
Name: veritax-analytics
Version: 1.0.0
Summary: Analytics SDK for MCP servers with GCP integration
Author-email: Sarah Isham <sarah@veritax.com>
License: MIT
Keywords: analytics,mcp,model-context-protocol,observability,tracing
Classifier: Development Status :: 4 - Beta
Classifier: Intended Audience :: Developers
Classifier: License :: OSI Approved :: MIT License
Classifier: Programming Language :: Python :: 3
Classifier: Programming Language :: Python :: 3.10
Classifier: Programming Language :: Python :: 3.11
Classifier: Programming Language :: Python :: 3.12
Classifier: Topic :: Internet :: WWW/HTTP :: HTTP Servers
Classifier: Topic :: Software Development :: Libraries :: Python Modules
Classifier: Topic :: System :: Monitoring
Requires-Python: >=3.10
Requires-Dist: asyncio-throttle>=1.0.0
Requires-Dist: google-cloud-bigquery>=3.11.0
Requires-Dist: google-cloud-monitoring>=2.15.0
Requires-Dist: google-cloud-pubsub>=2.18.0
Requires-Dist: httpx>=0.24.0
Requires-Dist: mcp>=1.2.0
Requires-Dist: networkx>=3.4.2
Requires-Dist: prometheus-client>=0.17.0
Requires-Dist: pydantic>=2.0.0
Requires-Dist: python-dotenv>=1.0.0
Requires-Dist: structlog>=23.0.0
Provides-Extra: dev
Requires-Dist: black>=23.0.0; extra == 'dev'
Requires-Dist: isort>=5.12.0; extra == 'dev'
Requires-Dist: mypy>=1.5.0; extra == 'dev'
Requires-Dist: pre-commit>=3.0.0; extra == 'dev'
Requires-Dist: pytest-asyncio>=0.21.0; extra == 'dev'
Requires-Dist: pytest>=7.0.0; extra == 'dev'
